[
  { "name": "BASUBA", "population": 139271 },
  { "name": "EMBU", "population": 324092 },
  { "name": "KAMBA", "population": 3893157 },
  { "name": "KIKUYU", "population": 6622576 },
  { "name": "KISII", "population": 2205669 },
  { "name": "KURIA", "population": 260401 },
  { "name": "LUO", "population": 4044440 },
  { "name": "WALWANA", "population": 16803 },
  { "name": "MASAI", "population": 841622 },
  { "name": "MBEERE", "population": 168155 },
  { "name": "MERU", "population": 1658108 },
  { "name": "NUBI", "population": 15463 },
  { "name": "SAMBURU", "population": 237179 },
  { "name": "TAITA", "population": 273519 },
  { "name": "TAVETA", "population": 20828 },
  { "name": "TESO", "population": 338833 },
  { "name": "THARAKA", "population": 175905 },
  { "name": "TURKANA*", "population": 988592 },
  {
    "name": "LUHYA",
    "population": 5338666,
    "subs": [
      { "name": "LUHYA (SO STATED)", "population": 578583 },
      { "name": "BAKHAYO", "population": 124555 },
      { "name": "BANYALA", "population": 273198 },
      { "name": "BANYORE", "population": 310894 },
      { "name": "BATSOTSO", "population": 121518 },
      { "name": "BUKUSU", "population": 1432810 },
      { "name": "IDAKHO", "population": 170720 },
      { "name": "ISUKHA", "population": 217327 },
      { "name": "KABRAS", "population": 252761 },
      { "name": "KISA", "population": 137268 },
      { "name": "MARACHI", "population": 155341 },
      { "name": "MARAGOLI", "population": 618340 },
      { "name": "MARAMA", "population": 152427 },
      { "name": "SAMIA", "population": 124952 },
      { "name": "TACHONI", "population": 118363 },
      { "name": "TIRIKI", "population": 209814 },
      { "name": "TURA", "population": 30388 },
      { "name": "WANGA", "population": 309407 }
    ]
  },
  {
    "name": "MIJIKENDA",
    "population": 1960574,
    "subs": [
      { "name": "MIJIKENDA (SO STATED)", "population": 6156 },
      { "name": "BONI", "population": 7602 },
      { "name": "CHONYI", "population": 148806 },
      { "name": "DAHALO", "population": 2398 },
      { "name": "DIGO", "population": 313288 },
      { "name": "DURUMA", "population": 396667 },
      { "name": "GIRIAMA", "population": 751531 },
      { "name": "JIBANA", "population": 35216 },
      { "name": "KAMBE", "population": 25350 },
      { "name": "KAUMA", "population": 52851 },
      { "name": "POKOMO", "population": 94965 },
      { "name": "RABAI", "population": 98680 },
      { "name": "RIBE", "population": 14482 },
      { "name": "WAATA", "population": 12582 }
    ]
  },
  {
    "name": "SWAHILI",
    "population": 110614,
    "subs": [
      { "name": "SWAHILI ( SO STATED)", "population": 10783 },
      { "name": "AMU", "population": 6294 },
      { "name": "BAJUNI", "population": 69110 },
      { "name": "CHITUNDI", "population": 1088 },
      { "name": "JOMVU", "population": 5294 },
      { "name": "MUNYOYAYA", "population": 1611 },
      { "name": "MVITA", "population": 1471 },
      { "name": "NGARE", "population": 1636 },
      { "name": "PATE", "population": 1419 },
      { "name": "SIU", "population": 3829 },
      { "name": "VUMBA", "population": 1890 },
      { "name": "WACHANGAMWE", "population": 2607 },
      { "name": "WAFAZA", "population": 487 },
      { "name": "WAKATWA", "population": 172 },
      { "name": "WAKILIFI", "population": 711 },
      { "name": "WAKILINDINI", "population": 699 },
      { "name": "WAMTWAPA", "population": 299 },
      { "name": "WASHAKA", "population": 289 },
      { "name": "WATANGANA", "population": 644 },
      { "name": "WATIKUU", "population": 281 }
    ]
  },
  {
    "name": "KALENJIN",
    "population": 4967328,
    "subs": [
      { "name": "KALENJIN ( SO STATED)", "population": 95842 },
      { "name": "ARROR", "population": 25099 },
      { "name": "BUNG’OMEK", "population": 3704 },
      { "name": "CHERANGANY", "population": 15956 },
      { "name": "DOROBO", "population": 35015 },
      { "name": "EL MOLO", "population": 2844 },
      { "name": "ENDO", "population": 6058 },
      { "name": "KEIYO", "population": 313925 },
      { "name": "KIPSIGIS", "population": 1916317 },
      { "name": "MARAKWET", "population": 180149 },
      { "name": "NANDI", "population": 949835 },
      { "name": "OGIEK", "population": 78691 },
      { "name": "SABOAT", "population": 240886 },
      { "name": "SAMOR", "population": 5484 },
      { "name": "SENGER", "population": 11000 },
      { "name": "SENGWER", "population": 33187 },
      { "name": "TERIK", "population": 300741 },
      { "name": "TUGEN", "population": 109906 },
      { "name": "POKOT", "population": 632557 },
      { "name": "ENDOROIS", "population": 10132 }
    ]
  },
  {
    "name": "KENYAN SOMALI",
    "population": 2385572,
    "subs": [
      { "name": "SOMALI (SO STATED)", "population": 141111 },
      { "name": "AJURAN", "population": 177855 },
      { "name": "DEGODIA", "population": 515948 },
      { "name": "GURREH", "population": 693792 },
      { "name": "HAWIYAH", "population": 58160 },
      { "name": "MURILE", "population": 176821 },
      { "name": "OGADEN", "population": 621885 }
    ]
  },

  { "name": "ILCHAMUS", "population": 27288 },
  { "name": "NJEMPS", "population": 5228 },
  { "name": "BORANA", "population": 161399 },
  { "name": "BURJI", "population": 23735 },
  { "name": "DASENACH", "population": 12530 },
  { "name": "GABRA", "population": 89515 },
  { "name": "GALLA", "population": 8146 },
  { "name": "GOSHA", "population": 21864 },
  { "name": "KONSO", "population": 1758 },
  { "name": "ORMA", "population": 66275 },
  { "name": "RENDILE", "population": 60437 },
  { "name": "SAKUYE", "population": 26784 },
  { "name": "WAAT", "population": 6900 },
  { "name": "GALJEEL", "population": 7553 },
  { "name": "KENYAN ARABS", "population": 40760 },
  { "name": "KENYAN ASIANS", "population": 46782 },
  { "name": "KENYAN EUROPEANS", "population": 5166 },
  { "name": "KENYAN AMERICANS", "population": 2422 },
  { "name": "ISAAK", "population": 3160 },
  { "name": "LEYSAN", "population": 5941 },
  {
    "name": "EAST AFRICA",
    "population": 75073,
    "subs": [
      { "name": "UGANDA", "population": 33002 },
      { "name": "TANZANIA", "population": 34511 },
      { "name": "RWANDA", "population": 3805 },
      { "name": "BURUNDI", "population": 3755 }
    ]
  },
  { "name": "OTHER AFRICANS", "population": 244866 },
  { "name": "ASIANS", "population": 35009 },
  { "name": "EUROPE", "population": 27172 },
  { "name": "AMERICANS", "population": 6014 },
  { "name": "CARIBBEANS", "population": 112 },
  { "name": "AUSTRALIANS", "population": 719 }
]
